tradx/__init__.py
tradx/algoContainer.py
tradx/dualHashMap.py
tradx/interactiveEngine.py
tradx/marketDataEngine.py
tradx/py.typed
tradx/baseClass/baseAlgo.py
tradx/baseClass/interactive/order.py
tradx/baseClass/interactive/orderEvent.py
tradx/baseClass/interactive/position.py
tradx/baseClass/interactive/positionEvent.py
tradx/baseClass/interactive/tradeConversionEvent.py
tradx/baseClass/interactive/tradeEvent.py
tradx/baseClass/market/candleData.py
tradx/baseClass/market/cmInstrument.py
tradx/baseClass/market/futureInstrument.py
tradx/baseClass/market/index.py
tradx/baseClass/market/instrumentPropertyChangeData.py
tradx/baseClass/market/ltpData.py
tradx/baseClass/market/ltpPartialData.py
tradx/baseClass/market/marketDepthData.py
tradx/baseClass/market/marketStatusData.py
tradx/baseClass/market/openInterestData.py
tradx/baseClass/market/openInterestPartialData.py
tradx/baseClass/market/optionsInstrument.py
tradx/baseClass/market/touchLineData.py
tradx/baseClass/market/touchLinePartialData.py
tradx/constants/holidays.py
tradx/logger/logger.py
tradx/logger/logger2.py
tradx-0.10.0.dist-info/METADATA
tradx-0.10.0.dist-info/WHEEL
tradx-0.10.0.dist-info/RECORD
