Metadata-Version: 2.4
Name: tradx
Version: 0.10.0
Summary: A Package Designed to simplify strategy development on package xts-api-client
Author-email: "jatin.kumawat" <jatin.kumawat@rmoneyindia.com>
Requires-Python: >=3.12
Requires-Dist: aiohttp==3.11.11
Requires-Dist: apscheduler>=3.11.0
Requires-Dist: pydantic==2.10.4
Requires-Dist: pytest==8.3.4
Requires-Dist: shortuuid==1.0.13
Requires-Dist: xts-api-client>=0.1.12
